credsweeper/__init__.py
credsweeper/__main__.py
credsweeper/app.py
credsweeper/main.py
credsweeper/py.typed
credsweeper/common/__init__.py
credsweeper/common/constants.py
credsweeper/common/keyword_checklist.py
credsweeper/common/keyword_checklist.txt
credsweeper/common/keyword_pattern.py
credsweeper/common/morpheme_checklist.txt
credsweeper/config/__init__.py
credsweeper/config/config.py
credsweeper/credentials/__init__.py
credsweeper/credentials/augment_candidates.py
credsweeper/credentials/candidate.py
credsweeper/credentials/candidate_group_generator.py
credsweeper/credentials/candidate_key.py
credsweeper/credentials/credential_manager.py
credsweeper/credentials/line_data.py
credsweeper/deep_scanner/__init__.py
credsweeper/deep_scanner/abstract_scanner.py
credsweeper/deep_scanner/byte_scanner.py
credsweeper/deep_scanner/bzip2_scanner.py
credsweeper/deep_scanner/csv_scanner.py
credsweeper/deep_scanner/deb_scanner.py
credsweeper/deep_scanner/deep_scanner.py
credsweeper/deep_scanner/docx_scanner.py
credsweeper/deep_scanner/eml_scanner.py
credsweeper/deep_scanner/encoder_scanner.py
credsweeper/deep_scanner/gzip_scanner.py
credsweeper/deep_scanner/html_scanner.py
credsweeper/deep_scanner/jclass_scanner.py
credsweeper/deep_scanner/jks_scanner.py
credsweeper/deep_scanner/lang_scanner.py
credsweeper/deep_scanner/lzma_scanner.py
credsweeper/deep_scanner/mxfile_scanner.py
credsweeper/deep_scanner/patch_scanner.py
credsweeper/deep_scanner/pdf_scanner.py
credsweeper/deep_scanner/pkcs_scanner.py
credsweeper/deep_scanner/png_scanner.py
credsweeper/deep_scanner/pptx_scanner.py
credsweeper/deep_scanner/rpm_scanner.py
credsweeper/deep_scanner/rtf_scanner.py
credsweeper/deep_scanner/sqlite3_scanner.py
credsweeper/deep_scanner/strings_scanner.py
credsweeper/deep_scanner/tar_scanner.py
credsweeper/deep_scanner/tmx_scanner.py
credsweeper/deep_scanner/xlsx_scanner.py
credsweeper/deep_scanner/xml_scanner.py
credsweeper/deep_scanner/zip_scanner.py
credsweeper-1.14.7.dist-info/METADATA
credsweeper-1.14.7.dist-info/WHEEL
credsweeper-1.14.7.dist-info/entry_points.txt
credsweeper-1.14.7.dist-info/licenses/LICENSE
credsweeper-1.14.7.dist-info/RECORD
