Metadata-Version: 2.4
Name: credsweeper
Version: 1.14.7
Summary: Credential Sweeper
Project-URL: Homepage, https://github.com/Samsung/CredSweeper
Project-URL: Bug Tracker, https://github.com/Samsung/CredSweeper/issues
License: MIT
License-File: LICENSE
Classifier: License :: OSI Approved :: MIT License
Classifier: Operating System :: OS Independent
Classifier: Programming Language :: Python :: 3
Classifier: Programming Language :: Python :: 3 :: Only
Classifier: Programming Language :: Python :: 3.10
Classifier: Programming Language :: Python :: 3.11
Classifier: Programming Language :: Python :: 3.12
Classifier: Topic :: Security
Classifier: Topic :: Software Development :: Quality Assurance
Requires-Python: >=3.10
Requires-Dist: base58
Requires-Dist: beautifulsoup4>=4.11.0
Requires-Dist: colorama
Requires-Dist: cryptography
Requires-Dist: gitpython
Requires-Dist: humanfriendly
Requires-Dist: lxml
Requires-Dist: numpy
Requires-Dist: odfpy
Requires-Dist: onnxruntime; platform_system != 'Windows' or python_version != '3.12'
Requires-Dist: onnxruntime==1.19.2; platform_system == 'Windows' and python_version == '3.12'
Requires-Dist: openpyxl
Requires-Dist: pandas
Requires-Dist: pdfminer-six
Requires-Dist: pybase62
Requires-Dist: pyjks
Requires-Dist: python-dateutil
Requires-Dist: python-docx
Requires-Dist: python-pptx
Requires-Dist: pyyaml
Requires-Dist: rpmfile
Requires-Dist: striprtf
Requires-Dist: whatthepatch
Requires-Dist: xlrd
